computer/Add.py
computer/Mul.py
computer/__init__.py
computer_m-1.1.dist-info/METADATA
computer_m-1.1.dist-info/WHEEL
computer_m-1.1.dist-info/top_level.txt
computer_m-1.1.dist-info/RECORD
