Metadata-Version: 2.1
Name: computer-m
Version: 1.1
Summary: 测试的计算模块
Author: xiejl
Author-email: xiejianglei163@163.com
License: UNKNOWN
Platform: UNKNOWN
